ngxcfm/__init__.py
ngxcfm/__main__.py
ngxcfm/format.py
ngxcfm/list_conf.py
ngxcfm/log.py
ngxcfm/main.py
ngxcfm/switch_conf.py
ngxcfm/transfer_nginx_files.py
ngxcfm/os_platform/_os_style.py
ngxcfm/os_platform/os_checkdir.py
ngxcfm/os_platform/os_file.py
ngxcfm/os_platform/os_symlink.py
ngxcfm/os_platform/os_tar.py
ngxcfm-0.3.0.dist-info/licenses/LICENSE
ngxcfm-0.3.0.dist-info/METADATA
ngxcfm-0.3.0.dist-info/WHEEL
ngxcfm-0.3.0.dist-info/entry_points.txt
ngxcfm-0.3.0.dist-info/top_level.txt
ngxcfm-0.3.0.dist-info/RECORD
