Metadata-Version: 2.4
Name: ngxcfm
Version: 0.3.0
Summary: A command-line tool for managing Nginx configurations
Author-email: Neboer <rubinposter@gmail.com>
License-Expression: MIT
Keywords: nginx,config,management,manager,cli,command-line,tool
Classifier: Development Status :: 3 - Alpha
Classifier: Intended Audience :: Developers
Classifier: Operating System :: OS Independent
Classifier: Environment :: Console
Classifier: Natural Language :: English
Classifier: Topic :: Internet :: WWW/HTTP
Classifier: Topic :: Internet :: WWW/HTTP :: HTTP Servers
Classifier: Topic :: Internet :: WWW/HTTP :: Site Management
Classifier: Topic :: Utilities
Classifier: Programming Language :: Python :: 3
Classifier: Programming Language :: Python :: 3.7
Classifier: Programming Language :: Python :: 3.8
Classifier: Programming Language :: Python :: 3.9
Classifier: Programming Language :: Python :: 3.10
Classifier: Programming Language :: Python :: 3.11
Classifier: Programming Language :: Python :: 3.12
Classifier: Programming Language :: Python :: 3.13
Classifier: Programming Language :: Python :: 3.14
Requires-Python: >=3.7
License-File: LICENSE
Requires-Dist: fabric
Requires-Dist: nginxfmt
Requires-Dist: colored
Requires-Dist: pydos2unix
Dynamic: license-file
